requests_debugger/__init__.py
requests_debugger/requests_debugger.py
requests_debugger-0.0.3.dist-info/METADATA
requests_debugger-0.0.3.dist-info/WHEEL
requests_debugger-0.0.3.dist-info/top_level.txt
requests_debugger-0.0.3.dist-info/RECORD
